glovebox/__init__.py
glovebox-0.0.1.dist-info/METADATA
glovebox-0.0.1.dist-info/WHEEL
glovebox-0.0.1.dist-info/top_level.txt
glovebox-0.0.1.dist-info/zip-safe
glovebox-0.0.1.dist-info/RECORD
